aws_cdk/aws_quickstarts/_jsii/__init__.py
aws_cdk/aws_quickstarts/_jsii/aws-quickstarts@0.35.0.jsii.tgz
aws_cdk.aws_quickstarts-0.35.0.dist-info/METADATA
aws_cdk.aws_quickstarts-0.35.0.dist-info/WHEEL
aws_cdk.aws_quickstarts-0.35.0.dist-info/top_level.txt
aws_cdk.aws_quickstarts-0.35.0.dist-info/RECORD
