Metadata-Version: 2.1
Name: aws-cdk.aws-quickstarts
Version: 0.35.0
Summary: AWS Quickstarts for the CDK
Home-page: https://github.com/awslabs/aws-cdk
Author: Amazon Web Services
License: UNKNOWN
Project-URL: Source, https://github.com/awslabs/aws-cdk.git
Platform: UNKNOWN
Requires-Python: >=3.6
Requires-Dist: jsii (~=0.11.3)
Requires-Dist: publication (>=0.0.3)
